cryptous/CAESAR.py
cryptous/RSA.py
cryptous/Tools.py
cryptous/XOR.py
cryptous/__init__.py
cryptous-0.0.5.dist-info/METADATA
cryptous-0.0.5.dist-info/WHEEL
cryptous-0.0.5.dist-info/top_level.txt
cryptous-0.0.5.dist-info/RECORD
