Metadata-Version: 2.1
Name: cryptous
Version: 0.0.5
Summary: The simplest encryption module for Python :)
Home-page: UNKNOWN
Author: Guimov
License: UNKNOWN
Platform: UNKNOWN
Classifier: Development Status :: 4 - Beta
Classifier: Operating System :: OS Independent
Classifier: Intended Audience :: Developers
Classifier: Intended Audience :: Education
Classifier: Intended Audience :: Telecommunications Industry
Classifier: Programming Language :: Python
Classifier: Topic :: Security
Classifier: Topic :: Security :: Cryptography
